setup.py
django_flash_message/__init__.py
django_flash_message/exceptions.py
django_flash_message/patch.py
django_flash_message/settings.py
django_flash_message/storage.py
django_flash_message/tests.py
django_flash_message/utils.py
django_flash_message.egg-info/PKG-INFO
django_flash_message.egg-info/SOURCES.txt
django_flash_message.egg-info/dependency_links.txt
django_flash_message.egg-info/entry_points.txt
django_flash_message.egg-info/pbr.json
django_flash_message.egg-info/requires.txt
django_flash_message.egg-info/top_level.txt
django_flash_message.egg-info/zip-safe