Metadata-Version: 1.1
Name: django-flash-message
Version: 0.1a2
Summary: a simple message util for django
Home-page: https://github.com/youngershen/django-flash-message
Author: younger shen
Author-email: younger.x.shen@gmail.com
License: MIT
Keywords: django-flash-message,django,message
Platform: UNKNOWN
Classifier: Development Status :: 2 - Pre-Alpha
Classifier: Environment :: Web Environment
Classifier: Framework :: Django
Classifier: Intended Audience :: Developers
Classifier: License :: OSI Approved :: MIT License
Classifier: Natural Language :: English
Classifier: Programming Language :: Python :: 2.7
